maya-stubs/OpenMaya.pyi
maya-stubs/OpenMayaAnim.pyi
maya-stubs/OpenMayaMPx.pyi
maya-stubs/OpenMayaRender.pyi
maya-stubs/OpenMayaUI.pyi
maya-stubs/__init__.pyi
maya-stubs/py.typed
maya-stubs/standalone.pyi
maya-stubs/api/MDGContextGuard.pyi
maya-stubs/api/OpenMaya.pyi
maya-stubs/api/OpenMayaAnim.pyi
maya-stubs/api/OpenMayaRender.pyi
maya-stubs/api/OpenMayaUI.pyi
maya-stubs/api/_OpenMayaAnim_py2.pyi
maya-stubs/api/_OpenMayaRender_py2.pyi
maya-stubs/api/_OpenMayaUI_py2.pyi
maya-stubs/api/_OpenMaya_py2.pyi
maya-stubs/api/__init__.pyi
maya-stubs/cmds/__init__.pyi
maya-stubs/mel/__init__.pyi
ufe-stubs/__init__.pyi
ufe-stubs/py.typed
types_maya_strict-2025.0.5.dist-info/METADATA
types_maya_strict-2025.0.5.dist-info/WHEEL
types_maya_strict-2025.0.5.dist-info/RECORD
